kcp_wrapper/__init__.py
kcp_wrapper/_kcp.so
kcp_wrapper/kcp.py
kcp_wrapper-0.2.18.dist-info/METADATA
kcp_wrapper-0.2.18.dist-info/WHEEL
kcp_wrapper-0.2.18.dist-info/top_level.txt
kcp_wrapper-0.2.18.dist-info/RECORD
