Metadata-Version: 2.1
Name: kcp-wrapper
Version: 0.2.18
Summary: kcp_wrapper
Home-page: https://github.com/dantezhu/kcp_wrapper
Author: dantezhu
Author-email: dantezhu <zny2008@gmail.com>
License: MIT
Project-URL: Homepage, https://github.com/dantezhu/kcp_wrapper
Platform: any
